youtube_downloader/__init__.py
youtube_downloader/cli.py
youtube_downloader/downloader.py
ytsnap-0.1.0.dist-info/METADATA
ytsnap-0.1.0.dist-info/WHEEL
ytsnap-0.1.0.dist-info/entry_points.txt
ytsnap-0.1.0.dist-info/licenses/LICENSE
ytsnap-0.1.0.dist-info/RECORD
