Metadata-Version: 2.4
Name: ytsnap
Version: 0.1.0
Summary: Fast and independent YouTube video downloader
Project-URL: Homepage, https://github.com/yourusername/ytsnap
Project-URL: Repository, https://github.com/yourusername/ytsnap
Author-email: Your Name <your.email@example.com>
License: MIT
License-File: LICENSE
Keywords: download,downloader,video,youtube,ytsnap
Classifier: Development Status :: 4 - Beta
Classifier: Intended Audience :: Developers
Classifier: License :: OSI Approved :: MIT License
Classifier: Programming Language :: Python :: 3
Classifier: Programming Language :: Python :: 3.8
Classifier: Programming Language :: Python :: 3.9
Classifier: Programming Language :: Python :: 3.10
Classifier: Programming Language :: Python :: 3.11
Classifier: Programming Language :: Python :: 3.12
Requires-Python: >=3.8
Requires-Dist: requests>=2.31.0
